settipy.py
settipy-1.10.0.dist-info/METADATA
settipy-1.10.0.dist-info/WHEEL
settipy-1.10.0.dist-info/top_level.txt
settipy-1.10.0.dist-info/RECORD
