Metadata-Version: 2.1
Name: settipy
Version: 1.10.0
Summary: settings should be simple, boring and forget-able. With settipy it will be just that.
Home-page: https://github.com/Attumm/settipy
Author: Melvin Bijman
Author-email: bijman.m.m@gmail.com
License: MIT
Platform: UNKNOWN
Classifier: Development Status :: 5 - Production/Stable
Classifier: Intended Audience :: Developers
Classifier: License :: OSI Approved :: MIT License
Classifier: Programming Language :: Python :: 3
Classifier: Programming Language :: Python :: 3.5
Classifier: Programming Language :: Python :: 3.6
Classifier: Programming Language :: Python :: 3.7
Classifier: Programming Language :: Python :: 3.8
Classifier: Programming Language :: Python :: 3.9
Requires-Dist: cryptography
